{
    "nodes": [
      {"id": "minac", "name": "Ministère des Arts et de la Culture", "acronyme": "MINAC", "fonction": "Ministère"},
      {"id": "secretariat_particulier_minac", "name": "secrétariat particulier", "acronyme": "SP_MINAC", "fonction": "Secrétariat Particulier", "parent": "minac"},
      {"id": "conseillers_techniques_minac", "name": "conseillers techniques", "acronyme": "CT_MINAC", "fonction": "Conseillers Techniques", "parent": "minac"},
      {"id": "inspection_generale_minac", "name": "inspection générale", "acronyme": "IG_MINAC", "fonction": "Inspection Generale", "parent": "minac"},
      {"id": "secretariat_general_minac", "name": "secrétariat général", "acronyme": "SG_MINAC", "fonction": "Secretariat General", "parent": "minac"},
      {"id": "division_affaires_juridiques_minac", "name": "Division des affaires juridiques", "acronyme": "DAJ_MINAC", "fonction": "Division", "parent": "secretariat_general_minac"},
      {"id": "cellule_etudes_reglementation_minac", "name": "Cellule des études et de la réglementation", "acronyme": "CER_MINAC", "fonction": "Cellule", "parent": "division_affaires_juridiques_minac"},
      {"id": "cellule_contentieux_minac", "name": "cellule du contentieux", "acronyme": "CC_MINAC", "fonction": "Cellule", "parent": "division_affaires_juridiques_minac"},
      {"id": "cellule_etudes_planification_cooperation_minac", "name": "Cellule des études de la planification et de la coopération", "acronyme": "CEPC_MINAC", "fonction": "Cellule", "parent": "secretariat_general_minac"},
      {"id": "cellule_suivi_minac", "name": "cellule de suivi", "acronyme": "CS_MINAC", "fonction": "Cellule", "parent": "secretariat_general_minac"},
      {"id": "cellule_communication_minac", "name": "Cellule de communication", "acronyme": "CCOM_MINAC", "fonction": "Cellule", "parent": "secretariat_general_minac"},
      {"id": "cellule_informatique_statistiques_minac", "name": "Cellule informatique et des statistiques", "acronyme": "CIS_MINAC", "fonction": "Cellule", "parent": "secretariat_general_minac"},
      {"id": "cellule_traduction_minac", "name": "cellule de traduction", "acronyme": "CTRAD_MINAC", "fonction": "Cellule", "parent": "secretariat_general_minac"},
      {"id": "sous_direction_accueil_courrier_liaison_minac", "name": "Sous-direction de l'accueil du courrier et de liaison", "acronyme": "SDACL_MINAC", "fonction": "Sous-direction", "parent": "secretariat_general_minac"},
      {"id": "service_accueil_orientation_minac", "name": "Service de l'accueil et de l'orientation", "acronyme": "SAO_MINAC", "fonction": "Service", "parent": "sous_direction_accueil_courrier_liaison_minac"},
      {"id": "service_courrier_liaison_minac", "name": "service du courrier et de liaison", "acronyme": "SCL_MINAC", "fonction": "Service", "parent": "sous_direction_accueil_courrier_liaison_minac"},
      {"id": "service_relance_minac", "name": "service de la relance", "acronyme": "SR_MINAC", "fonction": "Service", "parent": "sous_direction_accueil_courrier_liaison_minac"},
      {"id": "service_documentation_archives_minac", "name": "service de la documentation et des archives", "acronyme": "SDA_MINAC", "fonction": "Service", "parent": "secretariat_general_minac"},
      {"id": "direction_patrimoine_culturel_minac", "name": "direction du patrimoine culturel", "acronyme": "DPC_MINAC", "fonction": "Direction", "parent": "secretariat_general_minac"},
      {"id": "sous_direction_patrimoine_culturel_materiel_minac", "name": "sous-direction du patrimoine culturel matériel", "acronyme": "SDPCM_MINAC", "fonction": "Sous-direction", "parent": "direction_patrimoine_culturel_minac"},
      {"id": "service_patrimoine_culturel_immobilier_minac", "name": "service du patrimoine culturel immobilier", "acronyme": "SPCI_MINAC", "fonction": "Service", "parent": "sous_direction_patrimoine_culturel_materiel_minac"},
      {"id": "service_musees_minac", "name": "service des musées", "acronyme": "SM_MINAC", "fonction": "Service", "parent": "sous_direction_patrimoine_culturel_materiel_minac"},
      {"id": "service_archeologie_minac", "name": "service de l'archéologie", "acronyme": "SA_MINAC", "fonction": "Service", "parent": "sous_direction_patrimoine_culturel_materiel_minac"},
      {"id": "sous_direction_patrimoine_culturel_immateriel_minac", "name": "sous-direction du patrimoine culturel immatériel", "acronyme": "SDPCI_MINAC", "fonction": "Sous-direction", "parent": "direction_patrimoine_culturel_minac"},
      {"id": "service_patrimoine_vivant_anthropologique_minac", "name": "service du patrimoine vivant et anthropologique", "acronyme": "SPVA_MINAC", "fonction": "Service", "parent": "sous_direction_patrimoine_culturel_immateriel_minac"},
      {"id": "service_figures_historiques_fetes_minac", "name": "service des figures historiques et des fêtes commémoratives", "acronyme": "SFHF_MINAC", "fonction": "Service", "parent": "sous_direction_patrimoine_culturel_immateriel_minac"},
      {"id": "sous_direction_diversite_culturelle_minac", "name": "sous-direction de la diversité culturelle", "acronyme": "SDDC_MINAC", "fonction": "Sous-direction", "parent": "direction_patrimoine_culturel_minac"},
      {"id": "service_langues_maternelles_nationales_minac", "name": "service des langues maternelles et nationales", "acronyme": "SLMN_MINAC", "fonction": "Service", "parent": "sous_direction_diversite_culturelle_minac"},
      {"id": "service_expressions_valeurs_culturelles_minac", "name": "service des expressions et valeurs culturelles", "acronyme": "SEVC_MINAC", "fonction": "Service", "parent": "sous_direction_diversite_culturelle_minac"},
      {"id": "direction_developpement_promotion_arts_minac", "name": "direction du développement et de la promotion des arts", "acronyme": "DDPA_MINAC", "fonction": "Direction", "parent": "secretariat_general_minac"},
      {"id": "sous_direction_arts_vivants_minac", "name": "sous-direction des arts vivants", "acronyme": "SDAV_MINAC", "fonction": "Sous-direction", "parent": "direction_developpement_promotion_arts_minac"},
      {"id": "service_arts_lyriques_choregraphiques_minac", "name": "service des arts lyriques et chorégraphiques", "acronyme": "SALC_MINAC", "fonction": "Service", "parent": "sous_direction_arts_vivants_minac"},
      {"id": "service_arts_dramatiques_litteraires_minac", "name": "service des arts dramatiques et littéraires", "acronyme": "SADL_MINAC", "fonction": "Service", "parent": "sous_direction_arts_vivants_minac"},
      {"id": "sous_direction_arts_visuels_appliques_minac", "name": "sous-direction des arts visuels et appliqués", "acronyme": "SDAVA_MINAC", "fonction": "Sous-direction", "parent": "direction_developpement_promotion_arts_minac"},
      {"id": "service_arts_plastiques_minac", "name": "service des arts plastiques", "acronyme": "SAP_MINAC", "fonction": "Service", "parent": "sous_direction_arts_visuels_appliques_minac"},
      {"id": "service_arts_appliques_minac", "name": "service des arts appliqués", "acronyme": "SAA_MINAC", "fonction": "Service", "parent": "sous_direction_arts_visuels_appliques_minac"},
      {"id": "service_arts_multimedias_minac", "name": "service des arts multimédias", "acronyme": "SAM_MINAC", "fonction": "Service", "parent": "sous_direction_arts_visuels_appliques_minac"},
      {"id": "direction_archives_documents_administratifs_minac", "name": "direction des archives et des documents administratifs", "acronyme": "DADA_MINAC", "fonction": "Direction", "parent": "secretariat_general_minac"},
      {"id": "sous_direction_normes_reglementation_controle_archivistique_minac", "name": "sous-direction des normes de la réglementation et du contrôle archivistique", "acronyme": "SDNRCA_MINAC", "fonction": "Sous-direction", "parent": "direction_archives_documents_administratifs_minac"},
      {"id": "service_normalisation_reglementation_archivistique_minac", "name": "service de la normalisation et de la réglementation archivistique", "acronyme": "SNRA_MINAC", "fonction": "Service", "parent": "sous_direction_normes_reglementation_controle_archivistique_minac"},
      {"id": "service_technologies_archivistiques_minac", "name": "service des technologies archivistiques", "acronyme": "STA_MINAC", "fonction": "Service", "parent": "sous_direction_normes_reglementation_controle_archivistique_minac"},
      {"id": "service_controle_archivistique_minac", "name": "service du contrôle archivistique", "acronyme": "SCA_MINAC", "fonction": "Service", "parent": "sous_direction_normes_reglementation_controle_archivistique_minac"},
      {"id": "cellule_developpement_professionnel_minac", "name": "cellule du développement professionnel", "acronyme": "CDP_MINAC", "fonction": "Cellule", "parent": "direction_archives_documents_administratifs_minac"},
      {"id": "direction_livre_lecture_minac", "name": "direction du livre et de la lecture", "acronyme": "DLL_MINAC", "fonction": "Direction", "parent": "secretariat_general_minac"},
      {"id": "sous_direction_economie_livre_minac", "name": "sous-direction de l'économie du livre", "acronyme": "SDEL_MINAC", "fonction": "Sous-direction", "parent": "direction_livre_lecture_minac"},
      {"id": "service_creation_litteraire_minac", "name": "service de la création littéraire", "acronyme": "SCL_MINAC", "fonction": "Service", "parent": "sous_direction_economie_livre_minac"},
      {"id": "service_conseil_edition_minac", "name": "service du conseil et de l'édition", "acronyme": "SCE_MINAC", "fonction": "Service", "parent": "sous_direction_economie_livre_minac"},
      {"id": "sous_direction_developpement_lecture_bibliotheques_minac", "name": "sous-direction du développement de la lecture et des bibliothèques", "acronyme": "SDDLB_MINAC", "fonction": "Sous-direction", "parent": "direction_livre_lecture_minac"},
      {"id": "service_developpement_lecture_publique_minac", "name": "service du développement de la lecture publique", "acronyme": "SDLP_MINAC", "fonction": "Service", "parent": "sous_direction_developpement_lecture_bibliotheques_minac"},
      {"id": "service_bibliotheques_minac", "name": "service des bibliothèques", "acronyme": "SB_MINAC", "fonction": "Service", "parent": "sous_direction_developpement_lecture_bibliotheques_minac"},
      {"id": "direction_cinematographie_productions_audiovisuelles_minac", "name": "direction de la cinématographie et des productions audiovisuelles", "acronyme": "DCPA_MINAC", "fonction": "Direction", "parent": "secretariat_general_minac"},
      {"id": "sous_direction_cinematographie_normes_controles_minac", "name": "sous-direction de la cinématographie des normes et des contrôles", "acronyme": "SDCN_MINAC", "fonction": "Sous-direction", "parent": "direction_cinematographie_productions_audiovisuelles_minac"},
      {"id": "service_cinematographie_audiovisuel_minac", "name": "service de la cinématographie et de l'audiovisuel", "acronyme": "SCA_MINAC", "fonction": "Service", "parent": "sous_direction_cinematographie_normes_controles_minac"},
      {"id": "service_normes_controles_minac", "name": "service des normes et des contrôles", "acronyme": "SNC_MINAC", "fonction": "Service", "parent": "sous_direction_cinematographie_normes_controles_minac"},
      {"id": "sous_direction_audiovisuel_minac", "name": "sous-direction de l'audiovisuel", "acronyme": "SDA_MINAC", "fonction": "Sous-direction", "parent": "direction_cinematographie_productions_audiovisuelles_minac"},
      {"id": "service_cinematheque_projections_minac", "name": "service de la cinémathèque et des projections", "acronyme": "SCP_MINAC", "fonction": "Service", "parent": "sous_direction_audiovisuel_minac"},
      {"id": "service_statistiques_fichier_video_audiovisuel_minac", "name": "service des statistiques du fichier vidéo et audiovisuel", "acronyme": "SSFVA_MINAC", "fonction": "Service", "parent": "sous_direction_audiovisuel_minac"},
      {"id": "direction_spectacles_industries_creatives_minac", "name": "direction des spectacles et des industries créatives", "acronyme": "DSIC_MINAC", "fonction": "Direction", "parent": "secretariat_general_minac"},
      {"id": "sous_direction_spectacles_developpement_infrastructures_minac", "name": "sous-direction des spectacles et du développement des infrastructures et équipements techniques", "acronyme": "SDSDIET_MINAC", "fonction": "Sous-direction", "parent": "direction_spectacles_industries_creatives_minac"},
      {"id": "service_spectacles_minac", "name": "service des spectacles", "acronyme": "SS_MINAC", "fonction": "Service", "parent": "sous_direction_spectacles_developpement_infrastructures_minac"},
      {"id": "service_equipements_diffusion_minac", "name": "service des équipements de diffusion", "acronyme": "SED_MINAC", "fonction": "Service", "parent": "sous_direction_spectacles_developpement_infrastructures_minac"},
      {"id": "sous_direction_industries_creatives_minac", "name": "sous-direction des industries créatives", "acronyme": "SDIC_MINAC", "fonction": "Sous-direction", "parent": "direction_spectacles_industries_creatives_minac"},
      {"id": "service_productions_musicales_dramaturgiques_choregraphiques_minac", "name": "service des productions musicales dramaturgiques et chorégraphiques", "acronyme": "SPMDC_MINAC", "fonction": "Service", "parent": "sous_direction_industries_creatives_minac"},
      {"id": "service_commercialisation_consommation_minac", "name": "service de la commercialisation et de la consommation", "acronyme": "SCC_MINAC", "fonction": "Service", "parent": "sous_direction_industries_creatives_minac"},
      {"id": "direction_affaires_generales_minac", "name": "direction des affaires générales", "acronyme": "DAG_MINAC", "fonction": "Direction", "parent": "secretariat_general_minac"},
      {"id": "cellule_gestion_projet_sigipes_minac", "name": "cellule de gestion du projet sigipes", "acronyme": "CGPS_MINAC", "fonction": "Cellule", "parent": "direction_affaires_generales_minac"},
      {"id": "sous_direction_personnels_solde_pensions_minac", "name": "sous-direction des personnels de la solde et des pensions", "acronyme": "SDPSP_MINAC", "fonction": "Sous-direction", "parent": "direction_affaires_generales_minac"},
      {"id": "service_personnel_formation_stages_minac", "name": "service du personnel de la formation et des stages", "acronyme": "SPFS_MINAC", "fonction": "Service", "parent": "sous_direction_personnels_solde_pensions_minac"},
      {"id": "service_solde_pensions_minac", "name": "service de la solde et des pensions", "acronyme": "SSP_MINAC", "fonction": "Service", "parent": "sous_direction_personnels_solde_pensions_minac"},
      {"id": "service_action_sociale_minac", "name": "service de l'action sociale", "acronyme": "SAS_MINAC", "fonction": "Service", "parent": "sous_direction_personnels_solde_pensions_minac"},
      {"id": "sous_direction_budget_materiel_maintenance_minac", "name": "sous-direction du budget du matériel et de la maintenance", "acronyme": "SDBMM_MINAC", "fonction": "Sous-direction", "parent": "direction_affaires_generales_minac"},
      {"id": "service_budget_materiel_minac", "name": "service du budget et du matériel", "acronyme": "SBM_MINAC", "fonction": "Service", "parent": "sous_direction_budget_materiel_maintenance_minac"},
      {"id": "service_equipements_maintenance_minac", "name": "service des équipements et de la maintenance", "acronyme": "SEM_MINAC", "fonction": "Service", "parent": "sous_direction_budget_materiel_maintenance_minac"},
      {"id": "service_marches_publics_minac", "name": "service des marchés publics", "acronyme": "SMP_MINAC", "fonction": "Service", "parent": "sous_direction_budget_materiel_maintenance_minac"},
      {"id": "delegations_regionales_minac", "name": "délégations régionales des arts et de la culture", "acronyme": "DRAC_MINAC", "fonction": "Delegations Regionales", "parent": "minac"},
      {"id": "service_regional_patrimoine_culturel_musees_minac", "name": "service du patrimoine culturel et des musées", "acronyme": "SRPCM_MINAC", "fonction": "Service", "parent": "delegations_regionales_minac"},
      {"id": "service_regional_archives_livre_lecture_minac", "name": "service des archives du livre et de la lecture", "acronyme": "SRALL_MINAC", "fonction": "Service", "parent": "delegations_regionales_minac"},
      {"id": "service_regional_cinema_audiovisuel_minac", "name": "service du cinéma et de l'audiovisuel", "acronyme": "SRCA_MINAC", "fonction": "Service", "parent": "delegations_regionales_minac"},
      {"id": "service_regional_arts_spectacles_entreprises_culturelles_industries_creatives_minac", "name": "service des arts des spectacles des entreprises culturelles et des industries créatives", "acronyme": "SRASECIC_MINAC", "fonction": "Service", "parent": "delegations_regionales_minac"},
      {"id": "service_regional_affaires_generales_minac", "name": "service des affaires générales", "acronyme": "SRAG_MINAC", "fonction": "Service", "parent": "delegations_regionales_minac"},
      {"id": "delegations_departementales_minac", "name": "délégations départementales des arts et de la culture", "acronyme": "DDAC_MINAC", "fonction": "Delegations Departementales", "parent": "delegations_regionales_minac"},
      {"id": "bureau_departemental_patrimoine_culturel_archives_musees_minac", "name": "bureau du patrimoine culturel des archives et des musées", "acronyme": "BDPCAM_MINAC", "fonction": "Bureau", "parent": "delegations_departementales_minac"},
      {"id": "bureau_departemental_cinema_audiovisuel_minac", "name": "bureau du cinéma et de l'audiovisuel", "acronyme": "BDCA_MINAC", "fonction": "Bureau", "parent": "delegations_departementales_minac"},
      {"id": "bureau_departemental_action_culturelle_livre_lecture_minac", "name": "bureau de l'action culturelle du livre et de la lecture", "acronyme": "BDACLL_MINAC", "fonction": "Bureau", "parent": "delegations_departementales_minac"},
      {"id": "bureau_departemental_affaires_generales_minac", "name": "bureau des affaires générales", "acronyme": "BDAG_MINAC", "fonction": "Bureau", "parent": "delegations_departementales_minac"},
      {"id": "ensemble_national_minac", "name": "ensemble national", "acronyme": "EN_MINAC", "fonction": "Service Rattache", "parent": "minac"},
      {"id": "musee_national_minac", "name": "musée national", "acronyme": "MN_MINAC", "fonction": "Service Rattache", "parent": "minac"},
      {"id": "bibliotheque_nationale_minac", "name": "bibliothèque nationale", "acronyme": "BN_MINAC", "fonction": "Service Rattache", "parent": "minac"},
      {"id": "archives_nationales_minac", "name": "archives nationales", "acronyme": "AN_MINAC", "fonction": "Service Rattache", "parent": "minac"},
      {"id": "cinematheque_nationale_minac", "name": "cinémathèque nationale", "acronyme": "CN_MINAC", "fonction": "Service Rattache", "parent": "minac"},
      {"id": "centrale_lecture_publique_minac", "name": "centrale de lecture publique", "acronyme": "CLP_MINAC", "fonction": "Service Rattache", "parent": "minac"},
      {"id": "institut_national_arts_culture_minac", "name": "institut national des arts et de la culture", "acronyme": "INAC_MINAC", "fonction": "Service Rattache", "parent": "minac"}
    ],
    "edges": [
      {"source": "minac", "target": "secretariat_particulier_minac"},
      {"source": "minac", "target": "conseillers_techniques_minac"},
      {"source": "minac", "target": "inspection_generale_minac"},
      {"source": "minac", "target": "secretariat_general_minac"},
      {"source": "minac", "target": "delegations_regionales_minac"},
      {"source": "minac", "target": "ensemble_national_minac"},
      {"source": "minac", "target": "musee_national_minac"},
      {"source": "minac", "target": "bibliotheque_nationale_minac"},
      {"source": "minac", "target": "archives_nationales_minac"},
      {"source": "minac", "target": "cinematheque_nationale_minac"},
      {"source": "minac", "target": "centrale_lecture_publique_minac"},
      {"source": "minac", "target": "institut_national_arts_culture_minac"},
      {"source": "secretariat_general_minac", "target": "division_affaires_juridiques_minac"},
      {"source": "division_affaires_juridiques_minac", "target": "cellule_etudes_reglementation_minac"},
      {"source": "division_affaires_juridiques_minac", "target": "cellule_contentieux_minac"},
      {"source": "secretariat_general_minac", "target": "cellule_etudes_planification_cooperation_minac"},
      {"source": "secretariat_general_minac", "target": "cellule_suivi_minac"},
      {"source": "secretariat_general_minac", "target": "cellule_communication_minac"},
      {"source": "secretariat_general_minac", "target": "cellule_informatique_statistiques_minac"},
      {"source": "secretariat_general_minac", "target": "cellule_traduction_minac"},
      {"source": "secretariat_general_minac", "target": "sous_direction_accueil_courrier_liaison_minac"},
      {"source": "sous_direction_accueil_courrier_liaison_minac", "target": "service_accueil_orientation_minac"},
      {"source": "sous_direction_accueil_courrier_liaison_minac", "target": "service_courrier_liaison_minac"},
      {"source": "sous_direction_accueil_courrier_liaison_minac", "target": "service_relance_minac"},
      {"source": "secretariat_general_minac", "target": "service_documentation_archives_minac"},
      {"source": "secretariat_general_minac", "target": "direction_patrimoine_culturel_minac"},
      {"source": "direction_patrimoine_culturel_minac", "target": "sous_direction_patrimoine_culturel_materiel_minac"},
      {"source": "sous_direction_patrimoine_culturel_materiel_minac", "target": "service_patrimoine_culturel_immobilier_minac"},
      {"source": "sous_direction_patrimoine_culturel_materiel_minac", "target": "service_musees_minac"},
      {"source": "sous_direction_patrimoine_culturel_materiel_minac", "target": "service_archeologie_minac"},
      {"source": "direction_patrimoine_culturel_minac", "target": "sous_direction_patrimoine_culturel_immateriel_minac"},
      {"source": "sous_direction_patrimoine_culturel_immateriel_minac", "target": "service_patrimoine_vivant_anthropologique_minac"},
      {"source": "sous_direction_patrimoine_culturel_immateriel_minac", "target": "service_figures_historiques_fetes_minac"},
      {"source": "direction_patrimoine_culturel_minac", "target": "sous_direction_diversite_culturelle_minac"},
      {"source": "sous_direction_diversite_culturelle_minac", "target": "service_langues_maternelles_nationales_minac"},
      {"source": "sous_direction_diversite_culturelle_minac", "target": "service_expressions_valeurs_culturelles_minac"},
      {"source": "secretariat_general_minac", "target": "direction_developpement_promotion_arts_minac"},
      {"source": "direction_developpement_promotion_arts_minac", "target": "sous_direction_arts_vivants_minac"},
      {"source": "sous_direction_arts_vivants_minac", "target": "service_arts_lyriques_choregraphiques_minac"},
      {"source": "sous_direction_arts_vivants_minac", "target": "service_arts_dramatiques_litteraires_minac"},
      {"source": "direction_developpement_promotion_arts_minac", "target": "sous_direction_arts_visuels_appliques_minac"},
      {"source": "sous_direction_arts_visuels_appliques_minac", "target": "service_arts_plastiques_minac"},
      {"source": "sous_direction_arts_visuels_appliques_minac", "target": "service_arts_appliques_minac"},
      {"source": "sous_direction_arts_visuels_appliques_minac", "target": "service_arts_multimedias_minac"},
      {"source": "secretariat_general_minac", "target": "direction_archives_documents_administratifs_minac"},
      {"source": "direction_archives_documents_administratifs_minac", "target": "sous_direction_normes_reglementation_controle_archivistique_minac"},
      {"source": "sous_direction_normes_reglementation_controle_archivistique_minac", "target": "service_normalisation_reglementation_archivistique_minac"},
      {"source": "sous_direction_normes_reglementation_controle_archivistique_minac", "target": "service_technologies_archivistiques_minac"},
      {"source": "sous_direction_normes_reglementation_controle_archivistique_minac", "target": "service_controle_archivistique_minac"},
      {"source": "direction_archives_documents_administratifs_minac", "target": "cellule_developpement_professionnel_minac"},
      {"source": "secretariat_general_minac", "target": "direction_livre_lecture_minac"},
      {"source": "direction_livre_lecture_minac", "target": "sous_direction_economie_livre_minac"},
      {"source": "sous_direction_economie_livre_minac", "target": "service_creation_litteraire_minac"},
      {"source": "sous_direction_economie_livre_minac", "target": "service_conseil_edition_minac"},
      {"source": "direction_livre_lecture_minac", "target": "sous_direction_developpement_lecture_bibliotheques_minac"},
      {"source": "sous_direction_developpement_lecture_bibliotheques_minac", "target": "service_developpement_lecture_publique_minac"},
      {"source": "sous_direction_developpement_lecture_bibliotheques_minac", "target": "service_bibliotheques_minac"},
      {"source": "secretariat_general_minac", "target": "direction_cinematographie_productions_audiovisuelles_minac"},
      {"source": "direction_cinematographie_productions_audiovisuelles_minac", "target": "sous_direction_cinematographie_normes_controles_minac"},
      {"source": "sous_direction_cinematographie_normes_controles_minac", "target": "service_cinematographie_audiovisuel_minac"},
      {"source": "sous_direction_cinematographie_normes_controles_minac", "target": "service_normes_controles_minac"},
      {"source": "direction_cinematographie_productions_audiovisuelles_minac", "target": "sous_direction_audiovisuel_minac"},
      {"source": "sous_direction_audiovisuel_minac", "target": "service_cinematheque_projections_minac"},
      {"source": "sous_direction_audiovisuel_minac", "target": "service_statistiques_fichier_video_audiovisuel_minac"},
      {"source": "secretariat_general_minac", "target": "direction_spectacles_industries_creatives_minac"},
      {"source": "direction_spectacles_industries_creatives_minac", "target": "sous_direction_spectacles_developpement_infrastructures_minac"},
      {"source": "sous_direction_spectacles_developpement_infrastructures_minac", "target": "service_spectacles_minac"},
      {"source": "sous_direction_spectacles_developpement_infrastructures_minac", "target": "service_equipements_diffusion_minac"},
      {"source": "direction_spectacles_industries_creatives_minac", "target": "sous_direction_industries_creatives_minac"},
      {"source": "sous_direction_industries_creatives_minac", "target": "service_productions_musicales_dramaturgiques_choregraphiques_minac"},
      {"source": "sous_direction_industries_creatives_minac", "target": "service_commercialisation_consommation_minac"},
      {"source": "secretariat_general_minac", "target": "direction_affaires_generales_minac"},
      {"source": "direction_affaires_generales_minac", "target": "cellule_gestion_projet_sigipes_minac"},
      {"source": "direction_affaires_generales_minac", "target": "sous_direction_personnels_solde_pensions_minac"},
      {"source": "sous_direction_personnels_solde_pensions_minac", "target": "service_personnel_formation_stages_minac"},
      {"source": "sous_direction_personnels_solde_pensions_minac", "target": "service_solde_pensions_minac"},
      {"source": "sous_direction_personnels_solde_pensions_minac", "target": "service_action_sociale_minac"},
      {"source": "direction_affaires_generales_minac", "target": "sous_direction_budget_materiel_maintenance_minac"},
      {"source": "sous_direction_budget_materiel_maintenance_minac", "target": "service_budget_materiel_minac"},
      {"source": "sous_direction_budget_materiel_maintenance_minac", "target": "service_equipements_maintenance_minac"},
      {"source": "sous_direction_budget_materiel_maintenance_minac", "target": "service_marches_publics_minac"},
      {"source": "delegations_regionales_minac", "target": "delegations_departementales_minac"},
      {"source": "delegations_regionales_minac", "target": "service_regional_patrimoine_culturel_musees_minac"},
      {"source": "delegations_regionales_minac", "target": "service_regional_archives_livre_lecture_minac"},
      {"source": "delegations_regionales_minac", "target": "service_regional_cinema_audiovisuel_minac"},
      {"source": "delegations_regionales_minac", "target": "service_regional_arts_spectacles_entreprises_culturelles_industries_creatives_minac"},
      {"source": "delegations_regionales_minac", "target": "service_regional_affaires_generales_minac"},
      {"source": "delegations_departementales_minac", "target": "bureau_departemental_patrimoine_culturel_archives_musees_minac"},
      {"source": "delegations_departementales_minac", "target": "bureau_departemental_cinema_audiovisuel_minac"},
      {"source": "delegations_departementales_minac", "target": "bureau_departemental_action_culturelle_livre_lecture_minac"},
      {"source": "delegations_departementales_minac", "target": "bureau_departemental_affaires_generales_minac"}
    ]
  }